qtbricks/__init__.py
qtbricks/aboutdialog.py
qtbricks/filebrowser.py
qtbricks/mainwindow.py
qtbricks/plot.py
qtbricks/testing.py
qtbricks/utils.py
qtbricks/widgets.py
qtbricks/__pycache__/__init__.cpython-311.pyc
qtbricks/__pycache__/__init__.cpython-39.pyc
qtbricks/__pycache__/aboutdialog.cpython-311.pyc
qtbricks/__pycache__/aboutdialog.cpython-39.pyc
qtbricks/__pycache__/filebrowser.cpython-311.pyc
qtbricks/__pycache__/filebrowser.cpython-39.pyc
qtbricks/__pycache__/mainwindow.cpython-311.pyc
qtbricks/__pycache__/mainwindow.cpython-39.pyc
qtbricks/__pycache__/plot.cpython-311.pyc
qtbricks/__pycache__/plot.cpython-39.pyc
qtbricks/__pycache__/testing.cpython-311.pyc
qtbricks/__pycache__/testing.cpython-39.pyc
qtbricks/__pycache__/utils.cpython-311.pyc
qtbricks/__pycache__/utils.cpython-39.pyc
qtbricks/__pycache__/widgets.cpython-311.pyc
qtbricks/images/LICENSE.txt
qtbricks/images/arrows-up-down-left-right.svg
qtbricks/images/backward-step.svg
qtbricks/images/chart-line.svg
qtbricks/images/circle-left.svg
qtbricks/images/circle-right.svg
qtbricks/images/circle-up.svg
qtbricks/images/floppy-disk.svg
qtbricks/images/forward-step.svg
qtbricks/images/hashtag.svg
qtbricks/images/house.svg
qtbricks/images/icon.svg
qtbricks/images/magnifying-glass.svg
qtbricks/images/plus.svg
qtbricks/images/share-from-square.svg
qtbricks/images/sliders.svg
qtbricks/images/tmp
qtbricks-0.1.0rc3.dist-info/licenses/LICENSE
qtbricks-0.1.0rc3.dist-info/METADATA
qtbricks-0.1.0rc3.dist-info/WHEEL
qtbricks-0.1.0rc3.dist-info/top_level.txt
qtbricks-0.1.0rc3.dist-info/RECORD
