Metadata-Version: 2.4
Name: qtbricks
Version: 0.1.0rc3
Summary: Python Qt components: widgets and utils, focussing on scientific GUIs
Home-page: https://pypi.org/project/qtbricks/
Author: Till Biskup
Author-email: code@till-biskup.de
License: BSD
Project-URL: Documentation, https://qtbricks.docs.till-biskup.de/
Project-URL: Source, https://github.com/tillbiskup/qtbricks
Keywords: Qt,widgets,building blocks,PySide6
Classifier: Programming Language :: Python :: 3
Classifier: Programming Language :: Python :: 3.9
Classifier: Programming Language :: Python :: 3.10
Classifier: Programming Language :: Python :: 3.11
Classifier: Programming Language :: Python :: 3.12
Classifier: License :: OSI Approved :: BSD License
Classifier: Operating System :: OS Independent
Classifier: Intended Audience :: Science/Research
Classifier: Intended Audience :: Developers
Classifier: Topic :: Scientific/Engineering :: Visualization
Classifier: Topic :: Software Development
Classifier: Development Status :: 4 - Beta
Requires-Python: >=3.9
License-File: LICENSE
Requires-Dist: PySide6
Requires-Dist: matplotlib
Provides-Extra: dev
Requires-Dist: prospector; extra == "dev"
Requires-Dist: pyroma; extra == "dev"
Requires-Dist: bandit; extra == "dev"
Requires-Dist: black; extra == "dev"
Requires-Dist: pymetacode; extra == "dev"
Provides-Extra: docs
Requires-Dist: sphinx; extra == "docs"
Requires-Dist: sphinx-rtd-theme; extra == "docs"
Requires-Dist: sphinx_multiversion; extra == "docs"
Provides-Extra: deployment
Requires-Dist: build; extra == "deployment"
Requires-Dist: twine; extra == "deployment"
Dynamic: author
Dynamic: author-email
Dynamic: classifier
Dynamic: description
Dynamic: description-content-type
Dynamic: home-page
Dynamic: keywords
Dynamic: license
Dynamic: license-file
Dynamic: project-url
Dynamic: provides-extra
Dynamic: requires-dist
Dynamic: requires-python
Dynamic: summary
